{
"faceStart":
[
"「んぷぅ！……\nんっはぁ……"
],
"faceWait":
[
"（フフ……気持ち\nよさそうにして……\nだらしない顔だな……",
"（フフン……口に\nチンポを入れるのも\n好きなんだな……"
],
"faceAfter":
[
"「派手に出したな……\n口の中……汚い精液で\nいっぱいだぞ……"
],

"titStart":
[
"「んっ…チンポが\n熱いっ……"
],
"titWait":
[
"「フフ……\n我慢汁で胸が\nベトベトだぞ……"
],
"titAfter":
[
"「フフン……\nたくさん出したな……\n凄いにおいだ……"
],

"normalStart":
[
"「んぅんっ……\nおマンコに……\nチンポきたっ……"
],
"normalWait":
[
"「フフン……どうした？\nさっさと腰を\n動かせ……"
],
"normalAfter":
[
"「派手に出したな……\nおマンコに\n出せて満足か？",
"「情けない顔で\nいったな……チンポが\n脈打って凄かったぞ"
],

"analStart":
[
"「んっ！…くぅ……\nお尻……きついっ……"
],
"analWait":
[
"（んんっ……くぅ……\n尻の穴はキツイな……",
"（んっ……尻の穴の\n違和感が凄いな……\nクセになりそうだ……"
],
"analAfter":
[
"「はぁ……派手にぶち\nまけたな……尻の穴が\nドロドロだぞ……"
],

"genericLoop":
[
"「はっ……はぁ……",
"「んっ……\nふぁん……くぅ……",
"「あぁん……\nはぁ……あぁ……"
],

"middleSensitivity":
[
"（んんっ……\nやばい……\nいきそう……"
],

"highSensitivity":
[
"（んっうぅ……\nダメだ……\nいっちゃう！……",
"（んんん……\nいくいくっ！……\nいっちゃう！……"
],

"maxSensitivity":
[
"「んんっ…いくっ……\nいくぅーーーー！……"
],

"orgasm":
[
"（はぁ…はぁ…"
]

}
